{"cameraMode":{"drawMode":0,"name":"Shaded","section":"Shading Mode"},"sceneLighting":false,"audioPlay":false,"sceneViewState":{"m_AlwaysRefresh":false,"showFog":true,"showSkybox":false,"showFlares":true,"showImageEffects":true,"showParticleSystems":true,"showVisualEffectGraphs":true,"m_FxEnabled":true},"in2DMode":false,"pivot":{"x":6.479921340942383,"y":0.30228281021118166,"z":-0.8603811264038086},"rotation":{"x":-0.21169500052928925,"y":-0.005279486533254385,"z":0.001146045047789812,"w":-0.9773358702659607},"size":4.508724212646484,"orthographic":false}